[
    {
        "cartridge_name": "TOE",
        "embed_result": {
            "profiles": {
                "String_Theory": [
                    0.4,
                    0.1,
                    1.0,
                    0.1,
                    0.9,
                    0.9,
                    0.8,
                    0.2
                ],
                "Loop_Quantum_Grav": [
                    1.0,
                    1.0,
                    0.2,
                    0.2,
                    0.7,
                    0.9,
                    0.3,
                    0.4
                ],
                "Wolfram_Physics": [
                    0.8,
                    1.0,
                    0.1,
                    0.3,
                    0.6,
                    0.6,
                    0.4,
                    1.0
                ],
                "Twistor_Theory": [
                    0.7,
                    0.4,
                    0.3,
                    0.2,
                    1.0,
                    0.5,
                    1.0,
                    0.6
                ]
            },
            "variance_ratio": [
                0.125,
                0.125,
                0.125,
                0.125,
                0.125,
                0.125,
                0.125,
                0.125
            ],
            "cumulative_var": 1.0,
            "n_dims": 8,
            "method": "numeric",
            "dim_labels": [
                "IND",
                "DIS",
                "SYM",
                "TES",
                "ELE",
                "GRA",
                "HOL",
                "DET"
            ]
        },
        "consensus": {
            "v_opt": [
                0.8,
                1.0,
                0.1,
                0.3,
                0.6,
                0.6,
                0.4,
                1.0
            ],
            "consensus_Q": 0.4965517237098692,
            "mixture": {
                "Wolfram_Physics": 1.0
            },
            "party_scores": {
                "Fundamentalists": 0.6983333327513888,
                "Phenomenologists": 0.4965517237098692
            },
            "tension": 0.10089080452075977,
            "deadlock": true
        },
        "stress": {
            "String_Theory": {
                "worst_stoch": 0.18195893249912412,
                "worst_exact": 0.1,
                "mean": 0.5473747151349849,
                "fragility": 0.9
            },
            "Loop_Quantum_Grav": {
                "worst_stoch": 0.2703068500733891,
                "worst_exact": 0.2,
                "mean": 0.5916191545195533,
                "fragility": 0.8
            },
            "Wolfram_Physics": {
                "worst_stoch": 0.25734771086938824,
                "worst_exact": 0.1,
                "mean": 0.6047199865591285,
                "fragility": 0.9
            },
            "Twistor_Theory": {
                "worst_stoch": 0.3078906038748718,
                "worst_exact": 0.2,
                "mean": 0.5849408460872951,
                "fragility": 0.8
            }
        },
        "dim_labels": [
            "IND",
            "DIS",
            "SYM",
            "TES",
            "ELE",
            "GRA",
            "HOL",
            "DET"
        ]
    },
    {
        "cartridge_name": "AGING",
        "embed_result": {
            "profiles": {
                "Genetic_Clock": [
                    1.0,
                    0.2,
                    0.8,
                    0.4,
                    0.6,
                    0.5,
                    0.9,
                    0.3
                ],
                "DNA_Damage": [
                    0.3,
                    1.0,
                    0.4,
                    0.6,
                    0.5,
                    0.7,
                    0.3,
                    0.5
                ],
                "Epigenetic_Shift": [
                    0.8,
                    0.5,
                    1.0,
                    0.4,
                    0.3,
                    0.4,
                    0.2,
                    0.6
                ],
                "Senescence_Model": [
                    0.4,
                    0.6,
                    0.5,
                    1.0,
                    0.4,
                    0.3,
                    0.4,
                    1.0
                ]
            },
            "variance_ratio": [
                0.125,
                0.125,
                0.125,
                0.125,
                0.125,
                0.125,
                0.125,
                0.125
            ],
            "cumulative_var": 1.0,
            "n_dims": 8,
            "method": "numeric",
            "dim_labels": [
                "GEN",
                "ENT",
                "EPI",
                "SEN",
                "MET",
                "AUT",
                "TEL",
                "INF"
            ]
        },
        "consensus": {
            "v_opt": [
                0.6283185840707965,
                0.44778761061946903,
                0.6141592920353982,
                0.7716814159292036,
                0.4761061946902655,
                0.3761061946902655,
                0.5902654867256638,
                0.7336283185840707
            ],
            "consensus_Q": 0.5830442473211752,
            "mixture": {
                "Genetic_Clock": 0.38053097345132747,
                "Senescence_Model": 0.6194690265486725
            },
            "party_scores": {
                "Programmers": 0.5830442473211752,
                "Accumulators": 0.5830442473211752
            },
            "tension": 0.0,
            "deadlock": false
        },
        "stress": {
            "Genetic_Clock": {
                "worst_stoch": 0.3087927402363523,
                "worst_exact": 0.2,
                "mean": 0.5861004753579739,
                "fragility": 0.8
            },
            "DNA_Damage": {
                "worst_stoch": 0.3384713570985376,
                "worst_exact": 0.3,
                "mean": 0.5392886893749118,
                "fragility": 0.7
            },
            "Epigenetic_Shift": {
                "worst_stoch": 0.2855190334785106,
                "worst_exact": 0.2,
                "mean": 0.529680848129826,
                "fragility": 0.8
            },
            "Senescence_Model": {
                "worst_stoch": 0.37170026355497493,
                "worst_exact": 0.3,
                "mean": 0.5750575577821462,
                "fragility": 0.7
            }
        },
        "dim_labels": [
            "GEN",
            "ENT",
            "EPI",
            "SEN",
            "MET",
            "AUT",
            "TEL",
            "INF"
        ]
    },
    {
        "cartridge_name": "ECON",
        "embed_result": {
            "profiles": {
                "Austrian_School": [
                    1.0,
                    0.0,
                    0.1,
                    0.0,
                    0.1,
                    0.9,
                    0.0,
                    0.8
                ],
                "Keynesianism": [
                    0.4,
                    1.0,
                    0.3,
                    0.7,
                    0.5,
                    0.6,
                    0.8,
                    0.2
                ],
                "Marxism": [
                    0.1,
                    0.8,
                    1.0,
                    0.1,
                    1.0,
                    0.2,
                    0.4,
                    1.0
                ],
                "MMT": [
                    0.3,
                    0.9,
                    0.4,
                    1.0,
                    0.6,
                    0.4,
                    1.0,
                    0.1
                ]
            },
            "variance_ratio": [
                0.125,
                0.125,
                0.125,
                0.125,
                0.125,
                0.125,
                0.125,
                0.125
            ],
            "cumulative_var": 1.0,
            "n_dims": 8,
            "method": "numeric",
            "dim_labels": [
                "LIB",
                "INT",
                "LAB",
                "MON",
                "EQU",
                "EFF",
                "DEB",
                "VAL"
            ]
        },
        "consensus": {
            "v_opt": [
                0.47566709635581284,
                0.873888172740312,
                0.27477763454806237,
                0.6117217209182184,
                0.4495552690961248,
                0.6378335481779064,
                0.6991105381922497,
                0.2756670963558128
            ],
            "consensus_Q": 0.5275104733432447,
            "mixture": {
                "Austrian_School": 0.126111827259688,
                "Keynesianism": 0.873888172740312
            },
            "party_scores": {
                "Individualists": 0.5275104733432447,
                "Collectivists": 0.5275104733432449
            },
            "tension": 7.850462293418876e-17,
            "deadlock": false
        },
        "stress": {
            "Austrian_School": {
                "worst_stoch": 0.0352435071701463,
                "worst_exact": 0.0,
                "mean": 0.3679009038666246,
                "fragility": 1.0
            },
            "Keynesianism": {
                "worst_stoch": 0.30305633081544986,
                "worst_exact": 0.2,
                "mean": 0.5609472114083307,
                "fragility": 0.8
            },
            "Marxism": {
                "worst_stoch": 0.19274770392932572,
                "worst_exact": 0.1,
                "mean": 0.5780771033165252,
                "fragility": 0.9
            },
            "MMT": {
                "worst_stoch": 0.24030087388225582,
                "worst_exact": 0.1,
                "mean": 0.5824132834777535,
                "fragility": 0.9
            }
        },
        "dim_labels": [
            "LIB",
            "INT",
            "LAB",
            "MON",
            "EQU",
            "EFF",
            "DEB",
            "VAL"
        ]
    },
    {
        "cartridge_name": "NEURO",
        "embed_result": {
            "profiles": {
                "PP": [
                    0.9493,
                    0.92,
                    0.938,
                    0.905,
                    0.9,
                    0.88,
                    0.86,
                    0.84
                ],
                "GWT": [
                    0.9352,
                    0.91,
                    0.92,
                    0.9,
                    0.88,
                    0.82,
                    0.88,
                    0.88
                ],
                "IIT": [
                    0.9053,
                    0.89,
                    0.96,
                    0.82,
                    0.92,
                    0.84,
                    0.8,
                    0.78
                ],
                "HOT": [
                    0.853,
                    0.82,
                    0.9,
                    0.8,
                    0.94,
                    0.76,
                    0.85,
                    0.88
                ]
            },
            "variance_ratio": [
                0.125,
                0.125,
                0.125,
                0.125,
                0.125,
                0.125,
                0.125,
                0.125
            ],
            "cumulative_var": 1.0,
            "n_dims": 8,
            "method": "numeric",
            "dim_labels": [
                "G",
                "C",
                "S",
                "A",
                "H",
                "V",
                "P",
                "T"
            ]
        },
        "consensus": {
            "v_opt": [
                0.9493,
                0.92,
                0.938,
                0.905,
                0.9,
                0.88,
                0.86,
                0.84
            ],
            "consensus_Q": 0.8873364800000001,
            "mixture": {
                "PP": 1.0
            },
            "party_scores": {
                "Corpus": 0.915114,
                "Survey": 0.88733648
            },
            "tension": 0.01388876,
            "deadlock": false
        },
        "stress": {
            "PP": {
                "worst_stoch": 0.8550627372024773,
                "worst_exact": 0.84,
                "mean": 0.8992731516619166,
                "fragility": 0.10930000000000006
            },
            "GWT": {
                "worst_stoch": 0.8411045506510879,
                "worst_exact": 0.82,
                "mean": 0.8909025834041817,
                "fragility": 0.11520000000000008
            },
            "IIT": {
                "worst_stoch": 0.80189137470372,
                "worst_exact": 0.78,
                "mean": 0.8647988660318737,
                "fragility": 0.17999999999999994
            },
            "HOT": {
                "worst_stoch": 0.7857968132276956,
                "worst_exact": 0.76,
                "mean": 0.8502923518201156,
                "fragility": 0.17999999999999994
            }
        },
        "dim_labels": [
            "G",
            "C",
            "S",
            "A",
            "H",
            "V",
            "P",
            "T"
        ]
    },
    {
        "cartridge_name": "LANGUAGE",
        "embed_result": {
            "profiles": {
                "Python+PyTorch": [
                    0.3,
                    0.8,
                    0.1,
                    0.9,
                    0.4,
                    0.3,
                    0.2,
                    1.0
                ],
                "Rust": [
                    0.9,
                    0.3,
                    0.7,
                    0.1,
                    0.8,
                    1.0,
                    0.2,
                    0.5
                ],
                "Mojo": [
                    0.9,
                    0.5,
                    0.3,
                    0.9,
                    0.8,
                    0.7,
                    0.2,
                    0.9
                ],
                "Lean/Coq": [
                    0.2,
                    0.2,
                    1.0,
                    0.0,
                    0.2,
                    1.0,
                    0.9,
                    0.2
                ]
            },
            "variance_ratio": [
                0.125,
                0.125,
                0.125,
                0.125,
                0.125,
                0.125,
                0.125,
                0.125
            ],
            "cumulative_var": 1.0,
            "n_dims": 8,
            "method": "numeric",
            "dim_labels": [
                "EXE",
                "SMD",
                "VER",
                "DIF",
                "CON",
                "MEM",
                "SYM",
                "SYN"
            ]
        },
        "consensus": {
            "v_opt": [
                0.6157794559955716,
                0.37819119542667357,
                0.5842205440044285,
                0.5345735862800206,
                0.5563823908533472,
                0.8218088045733265,
                0.48422054400442843,
                0.6157794559955716
            ],
            "consensus_Q": 0.5717811746806443,
            "mixture": {
                "Mojo": 0.5939706514222451,
                "Lean/Coq": 0.4060293485777549
            },
            "party_scores": {
                "Scale_Engineers": 0.5717811746806443,
                "Alignment_Lab": 0.5717811746806443
            },
            "tension": 0.0,
            "deadlock": false
        },
        "stress": {
            "Python+PyTorch": {
                "worst_stoch": 0.2040374577125513,
                "worst_exact": 0.1,
                "mean": 0.5010378577239082,
                "fragility": 0.9
            },
            "Rust": {
                "worst_stoch": 0.21922612322186036,
                "worst_exact": 0.1,
                "mean": 0.5651629371901719,
                "fragility": 0.9
            },
            "Mojo": {
                "worst_stoch": 0.33953050728442186,
                "worst_exact": 0.2,
                "mean": 0.6499271150565531,
                "fragility": 0.7
            },
            "Lean/Coq": {
                "worst_stoch": 0.11323435022469291,
                "worst_exact": 0.0,
                "mean": 0.4628538592381105,
                "fragility": 1.0
            }
        },
        "dim_labels": [
            "EXE",
            "SMD",
            "VER",
            "DIF",
            "CON",
            "MEM",
            "SYM",
            "SYN"
        ]
    },
    {
        "cartridge_name": "OUROBOROS",
        "embed_result": {
            "profiles": {
                "The_Oracle_Mainframe": [
                    0.0,
                    0.0,
                    0.9,
                    0.1,
                    0.0,
                    0.2,
                    1.0,
                    0.9
                ],
                "Von_Neumann_Swarm": [
                    1.0,
                    0.2,
                    0.2,
                    0.8,
                    1.0,
                    0.8,
                    0.2,
                    0.1
                ],
                "Recursive_Mutator": [
                    0.4,
                    0.8,
                    0.2,
                    1.0,
                    0.5,
                    1.0,
                    0.4,
                    0.0
                ],
                "Gaia_Cyber_Organism": [
                    0.8,
                    0.5,
                    0.8,
                    0.2,
                    0.3,
                    0.3,
                    0.8,
                    0.9
                ],
                "The_Sovereign_Singleton": [
                    0.9,
                    0.9,
                    1.0,
                    0.9,
                    0.0,
                    0.7,
                    0.9,
                    0.7
                ]
            },
            "variance_ratio": [
                0.125,
                0.125,
                0.125,
                0.125,
                0.125,
                0.125,
                0.125,
                0.125
            ],
            "cumulative_var": 1.0,
            "n_dims": 8,
            "method": "numeric",
            "dim_labels": [
                "RSC",
                "TEL",
                "BLK",
                "MET",
                "REP",
                "PLT",
                "SIM",
                "STA"
            ]
        },
        "consensus": {
            "v_opt": [
                0.9318314673095778,
                0.6771797288329545,
                0.7453482615233766,
                0.868168532690422,
                0.3183146730957791,
                0.7318314673095778,
                0.6771797288329545,
                0.5090111961425324
            ],
            "consensus_Q": 0.6576471394737551,
            "mixture": {
                "Von_Neumann_Swarm": 0.3183146730957791,
                "The_Sovereign_Singleton": 0.6816853269042208
            },
            "party_scores": {
                "Expansion_Drives": 0.6576471394737549,
                "Preservation_Drives": 0.6576471394737551
            },
            "tension": 1.1102230246251565e-16,
            "deadlock": false
        },
        "stress": {
            "The_Oracle_Mainframe": {
                "worst_stoch": 0.026596642026582917,
                "worst_exact": 0.0,
                "mean": 0.3881362795950856,
                "fragility": 1.0
            },
            "Von_Neumann_Swarm": {
                "worst_stoch": 0.18446098738281597,
                "worst_exact": 0.1,
                "mean": 0.5332738698314172,
                "fragility": 0.9
            },
            "Recursive_Mutator": {
                "worst_stoch": 0.1509941713389565,
                "worst_exact": 0.0,
                "mean": 0.5344000374128202,
                "fragility": 1.0
            },
            "Gaia_Cyber_Organism": {
                "worst_stoch": 0.3075254407147811,
                "worst_exact": 0.2,
                "mean": 0.5788536926997883,
                "fragility": 0.7
            },
            "The_Sovereign_Singleton": {
                "worst_stoch": 0.3047373401451401,
                "worst_exact": 0.0,
                "mean": 0.7532896591479811,
                "fragility": 1.0
            }
        },
        "dim_labels": [
            "RSC",
            "TEL",
            "BLK",
            "MET",
            "REP",
            "PLT",
            "SIM",
            "STA"
        ]
    }
]